openvino_telemetry/__init__.py
openvino_telemetry/main.py
openvino_telemetry/opt_in_out.py
openvino_telemetry/backend/__init__.py
openvino_telemetry/backend/backend.py
openvino_telemetry/backend/backend_ga.py
openvino_telemetry/backend/backend_ga4.py
openvino_telemetry/utils/__init__.py
openvino_telemetry/utils/cid.py
openvino_telemetry/utils/colored_print.py
openvino_telemetry/utils/input_with_timeout.py
openvino_telemetry/utils/message.py
openvino_telemetry/utils/opt_in_checker.py
openvino_telemetry/utils/params.py
openvino_telemetry/utils/sender.py
openvino_telemetry/utils/stats_processor.py
openvino_telemetry-2025.0.0.dist-info/LICENSE
openvino_telemetry-2025.0.0.dist-info/METADATA
openvino_telemetry-2025.0.0.dist-info/WHEEL
openvino_telemetry-2025.0.0.dist-info/entry_points.txt
openvino_telemetry-2025.0.0.dist-info/top_level.txt
openvino_telemetry-2025.0.0.dist-info/RECORD
