Metadata-Version: 2.1
Name: openvino-telemetry
Version: 2025.0.0
Summary: OpenVINO™ Telemetry package for sending statistics with user's consent, used in combination with other OpenVINO™ packages.
Home-page: https://github.com/openvinotoolkit/telemetry
Author: Intel® Corporation
Author-email: openvino_pushbot@intel.com
License: OSI Approved :: Apache Software License
Classifier: Programming Language :: Python :: 3
Classifier: License :: OSI Approved :: Apache Software License
Classifier: Operating System :: OS Independent
License-File: LICENSE
